MANIFEST.in
README.rst
setup.py
PSTymer.egg-info/PKG-INFO
PSTymer.egg-info/SOURCES.txt
PSTymer.egg-info/dependency_links.txt
PSTymer.egg-info/top_level.txt
PythonSimpleTimer/PythonTimer.py
PythonSimpleTimer/__init__.py