Metadata-Version: 1.1
Name: PSTymer
Version: 0.0.1
Summary: Monitor time for Python code
Home-page: https://github.com/Znax/python-simple-timer
Author: Znax & reco team
Author-email: UNKNOWN
License: UNKNOWN
Platform: UNKNOWN
Classifier: Development Status :: 3 - Alpha
Classifier: Intended Audience :: Developers
Classifier: Topic :: Software Development :: Build Tools
Classifier: License :: OSI Approved
Classifier: Programming Language :: Python :: 3.5
